easy_alert
