Metadata-Version: 1.0
Name: easy-alert
Version: 0.0.15
Summary: Super Simple Process Monitoring Tool
Home-page: https://github.com/mogproject/easy-alert
Author: mogproject
Author-email: mogproj@gmail.com
License: UNKNOWN
Platform: UNKNOWN
